display/__init__.py
display/display.py
tar_display-0.1.0.dist-info/LICENSE
tar_display-0.1.0.dist-info/METADATA
tar_display-0.1.0.dist-info/WHEEL
tar_display-0.1.0.dist-info/entry_points.txt
tar_display-0.1.0.dist-info/top_level.txt
tar_display-0.1.0.dist-info/RECORD
