Metadata-Version: 2.1
Name: tar_display
Version: 0.1.0
Summary: tar display application
Home-page: https://github.com/natthphong/display.git
Author: Your Name
Author-email: jaroenpronprasit@gmail.com
Classifier: Programming Language :: Python :: 3
Classifier: License :: OSI Approved :: MIT License
Classifier: Operating System :: OS Independent
License-File: LICENSE
Requires-Dist: tkinter
